{
    "initial state": "pp",
    "Ecom [GeV]": "13600",
    "process_id": [
        "pp13600_glsq"
    ],
    "process_latex": "$\\tilde g\\tilde q$",
    "PDF set": "NNLO PDF4LHC21",
    "order": "NNLOapprox+NNLL",
    "comment": "Gluino pair, squark-antisquark, squark-gluino(+antisquark-gluino), squakr pair (+antisquark pair) production cross sections. The cross-section values reported here assume a 8-fold squark degeneracy (i. e. ~u, ~d, ~c, ~s mass degenerate). Provided by the authors of NNLL-fast (arXiv:1607.07741), including the combined scale and PDF+AlphaS uncertainties. The PDF set used for the calculations is NNLO PDF4LHC21 Hessian (LHAPDF ID 93300), and renormalization scale is set equal to factorization scale.",
    "tool": "NNLL-fast",
    "reference": "?",
    "source": "",
    "contact": "christoph.borschensky@kit.edu,anna.kulesza@uni-muenster.de",
    "parameters": [
        [
            "gl"
        ],
        [
            "sq"
        ]
    ],
    "data": {
        "1250": {
            "3000": {
                "xsec_pb": 0.0001130004,
                "unc_pb": 2.766802363956e-05
            },
            "4000": {
                "xsec_pb": 1.101799e-06,
                "unc_pb": 1.1612785172159999e-06
            },
            "5000": {
                "xsec_pb": 5.118328e-09,
                "unc_pb": 2.3073786025288e-08
            },
            "6000": {
                "xsec_pb": 5.043275e-12,
                "unc_pb": 1.1438828542125e-10
            },
            "8000": {
                "xsec_pb": NaN,
                "unc_pb": NaN
            }
        },
        "1500": {
            "2500": {
                "xsec_pb": 0.0009809865,
                "unc_pb": 0.00012644062526745
            },
            "3000": {
                "xsec_pb": 0.000120588,
                "unc_pb": 2.86024003668e-05
            },
            "4000": {
                "xsec_pb": 1.229659e-06,
                "unc_pb": 1.277739896559e-06
            }
        },
        "1750": {
            "1500": {
                "xsec_pb": 0.04439226,
                "unc_pb": 0.0021904366310376
            },
            "2000": {
                "xsec_pb": 0.006834335,
                "unc_pb": 0.00052052133796115
            },
            "2500": {
                "xsec_pb": 0.0009783591,
                "unc_pb": 0.00012038121710039999
            },
            "3000": {
                "xsec_pb": 0.000125354,
                "unc_pb": 2.9012193003399998e-05
            },
            "3500": {
                "xsec_pb": 1.409024e-05,
                "unc_pb": 6.766775762944e-06
            },
            "4000": {
                "xsec_pb": 1.347572e-06,
                "unc_pb": 1.3831155590720003e-06
            },
            "5000": {
                "xsec_pb": 6.682107e-09,
                "unc_pb": 2.9401277482107e-08
            },
            "6000": {
                "xsec_pb": 7.086551e-12,
                "unc_pb": 1.5324333469603e-10
            },
            "8000": {
                "xsec_pb": NaN,
                "unc_pb": NaN
            }
        },
        "2250": {
            "1500": {
                "xsec_pb": 0.03485888,
                "unc_pb": 0.0014539251914432
            },
            "2000": {
                "xsec_pb": 0.005819106,
                "unc_pb": 0.00039157276355328004
            },
            "2500": {
                "xsec_pb": 0.0009108824,
                "unc_pb": 0.00010489448453680002
            },
            "3000": {
                "xsec_pb": 0.0001267359,
                "unc_pb": 2.8306818125520004e-05
            },
            "3500": {
                "xsec_pb": 1.51841e-05,
                "unc_pb": 7.13748511671e-06
            },
            "4000": {
                "xsec_pb": 1.527722e-06,
                "unc_pb": 1.541758709736e-06
            },
            "5000": {
                "xsec_pb": 8.161246e-09,
                "unc_pb": 3.541511492355e-08
            },
            "6000": {
                "xsec_pb": 9.268079e-12,
                "unc_pb": 1.9548009792903997e-10
            },
            "8000": {
                "xsec_pb": NaN,
                "unc_pb": NaN
            }
        },
        "2750": {
            "1000": {
                "xsec_pb": 0.1659901,
                "unc_pb": 0.004879518015244
            },
            "1500": {
                "xsec_pb": 0.02772828,
                "unc_pb": 0.0011009851859016002
            },
            "2000": {
                "xsec_pb": 0.004866712,
                "unc_pb": 0.00030219108423776
            },
            "2500": {
                "xsec_pb": 0.0008077107,
                "unc_pb": 9.012557147204999e-05
            },
            "3000": {
                "xsec_pb": 0.0001198053,
                "unc_pb": 2.629962351441e-05
            },
            "3500": {
                "xsec_pb": 1.52801e-05,
                "unc_pb": 7.06288700678e-06
            },
            "4000": {
                "xsec_pb": 1.617718e-06,
                "unc_pb": 1.616320291648e-06
            },
            "5000": {
                "xsec_pb": 9.359808e-09,
                "unc_pb": 4.0332872802048e-08
            },
            "6000": {
                "xsec_pb": 1.140467e-11,
                "unc_pb": 2.352434438098e-10
            },
            "8000": {
                "xsec_pb": NaN,
                "unc_pb": NaN
            }
        },
        "3250": {
            "1000": {
                "xsec_pb": 0.1292317,
                "unc_pb": 0.0039782738220680005
            },
            "1500": {
                "xsec_pb": 0.02238997,
                "unc_pb": 0.000870114536146
            },
            "2000": {
                "xsec_pb": 0.00407429,
                "unc_pb": 0.0002470362218555
            },
            "2500": {
                "xsec_pb": 0.0007039753,
                "unc_pb": 7.699948076093001e-05
            },
            "3000": {
                "xsec_pb": 0.0001091354,
                "unc_pb": 2.394875948432e-05
            },
            "3500": {
                "xsec_pb": 1.460774e-05,
                "unc_pb": 6.755530498976e-06
            },
            "4000": {
                "xsec_pb": 1.624462e-06,
                "unc_pb": 1.6151388876896e-06
            },
            "5000": {
                "xsec_pb": 1.016977e-08,
                "unc_pb": 4.332419649792e-08
            },
            "6000": {
                "xsec_pb": 1.325455e-11,
                "unc_pb": 2.686804646855e-10
            }
        },
        "4250": {
            "1000": {
                "xsec_pb": 0.0848486,
                "unc_pb": 0.0025977680103859997
            },
            "1500": {
                "xsec_pb": 0.01526459,
                "unc_pb": 0.0005870923118654
            },
            "2000": {
                "xsec_pb": 0.002911683,
                "unc_pb": 0.00017549362746308999
            },
            "2500": {
                "xsec_pb": 0.0005298896,
                "unc_pb": 5.821568503648e-05
            },
            "3000": {
                "xsec_pb": 8.708451e-05,
                "unc_pb": 1.9438499232042e-05
            },
            "3500": {
                "xsec_pb": 1.240988e-05,
                "unc_pb": 5.81641147696e-06
            },
            "4000": {
                "xsec_pb": 1.477168e-06,
                "unc_pb": 1.4778859036479998e-06
            }
        },
        "5250": {
            "1000": {
                "xsec_pb": 0.0605878,
                "unc_pb": 0.0018623496140339998
            },
            "1500": {
                "xsec_pb": 0.01096717,
                "unc_pb": 0.00043731480703300006
            },
            "2000": {
                "xsec_pb": 0.002153939,
                "unc_pb": 0.00013176583980404
            },
            "2500": {
                "xsec_pb": 0.0004041119,
                "unc_pb": 4.5096261312649995e-05
            },
            "3000": {
                "xsec_pb": 6.872642e-05,
                "unc_pb": 1.5609570614204e-05
            },
            "3500": {
                "xsec_pb": 1.018993e-05,
                "unc_pb": 4.861652286748e-06
            },
            "4000": {
                "xsec_pb": 1.26805e-06,
                "unc_pb": 1.28739917495e-06
            }
        },
        "6250": {
            "1000": {
                "xsec_pb": 0.04621016,
                "unc_pb": 0.0015920074788336
            },
            "1500": {
                "xsec_pb": 0.008234629,
                "unc_pb": 0.00033700293294161
            },
            "2000": {
                "xsec_pb": 0.001645987,
                "unc_pb": 0.00010189443019812
            },
            "2500": {
                "xsec_pb": 0.0003151451,
                "unc_pb": 3.590394549633e-05
            },
            "3000": {
                "xsec_pb": 5.479025e-05,
                "unc_pb": 1.2679751420874999e-05
            },
            "3500": {
                "xsec_pb": 8.3306e-06,
                "unc_pb": 4.04834337436e-06
            },
            "4000": {
                "xsec_pb": 1.066177e-06,
                "unc_pb": 1.100375693452e-06
            }
        },
        "8250": {
            "1000": {
                "xsec_pb": 0.03260282,
                "unc_pb": 0.0024069595893786
            },
            "1500": {
                "xsec_pb": 0.005144118,
                "unc_pb": 0.0002111475250752
            },
            "2000": {
                "xsec_pb": 0.001039226,
                "unc_pb": 6.644130350970001e-05
            },
            "2500": {
                "xsec_pb": 0.00020393,
                "unc_pb": 2.4017794571e-05
            },
            "3000": {
                "xsec_pb": 3.641815e-05,
                "unc_pb": 8.732660844905e-06
            },
            "3500": {
                "xsec_pb": 5.702752e-06,
                "unc_pb": 2.8633306790176e-06
            }
        }
    }
}